beneissue/__init__.py
beneissue/cli.py
beneissue/config.py
beneissue/graph/__init__.py
beneissue/graph/routing.py
beneissue/graph/state.py
beneissue/graph/workflow.py
beneissue/integrations/__init__.py
beneissue/integrations/claude_code.py
beneissue/integrations/git.py
beneissue/integrations/github.py
beneissue/labels.py
beneissue/metrics/__init__.py
beneissue/metrics/collector.py
beneissue/metrics/schemas.py
beneissue/metrics/storage.py
beneissue/mocks/__init__.py
beneissue/mocks/defaults.py
beneissue/mocks/loader.py
beneissue/nodes/__init__.py
beneissue/nodes/actions.py
beneissue/nodes/analyze.py
beneissue/nodes/fix.py
beneissue/nodes/intake.py
beneissue/nodes/load_preset.py
beneissue/nodes/schemas.py
beneissue/nodes/triage.py
beneissue/nodes/utils.py
beneissue/observability.py
beneissue/prompts/__init__.py
beneissue/prompts/analyze.md
beneissue/prompts/fix.md
beneissue/prompts/triage.md
beneissue/py.typed
beneissue/template/.claude/skills/beneissue/SKILL.md
beneissue/template/.claude/skills/beneissue/beneissue-config.yml
beneissue/template/.github/workflows/beneissue-test.yml
beneissue/template/.github/workflows/beneissue-workflow.yml
beneissue-2.0.18.dist-info/WHEEL
beneissue-2.0.18.dist-info/entry_points.txt
beneissue-2.0.18.dist-info/METADATA
beneissue-2.0.18.dist-info/RECORD
