Metadata-Version: 2.4
Name: beneissue
Version: 2.0.18
Summary: AI-powered GitHub issue automation framework
Keywords: github,automation,ai,issue-tracking,langgraph,claude,triage
Author: Benedict Lee
Author-email: Benedict Lee <leebd@hancom.com>
License-Expression: Apache-2.0
Classifier: Development Status :: 3 - Alpha
Classifier: Intended Audience :: Developers
Classifier: License :: OSI Approved :: Apache Software License
Classifier: Operating System :: OS Independent
Classifier: Programming Language :: Python :: 3
Classifier: Programming Language :: Python :: 3.11
Classifier: Programming Language :: Python :: 3.12
Classifier: Programming Language :: Python :: 3.13
Classifier: Topic :: Software Development :: Bug Tracking
Classifier: Topic :: Software Development :: Quality Assurance
Requires-Dist: langgraph>=0.2.0
Requires-Dist: langsmith>=0.1.0
Requires-Dist: langchain-anthropic>=0.2.0
Requires-Dist: pygithub>=2.0.0
Requires-Dist: pydantic>=2.0.0
Requires-Dist: typer>=0.9.0
Requires-Dist: pyyaml>=6.0.0
Requires-Dist: claude-agent-sdk>=0.1.0
Requires-Dist: supabase>=2.0.0
Requires-Python: >=3.11
Project-URL: Documentation, https://github.com/opendataloader-project/beneissue#readme
Project-URL: Homepage, https://github.com/opendataloader-project/beneissue
Project-URL: Issues, https://github.com/opendataloader-project/beneissue/issues
Project-URL: Repository, https://github.com/opendataloader-project/beneissue
